<rdf:RDF
    xmlns:config="info:fedoraconfig/"
    xmlns:acl="http://www.w3.org/ns/auth/acl#"
    xmlns:ns010="http://purl.org/dc/elements/1.1/format:"
    xmlns:ns012="http://purl.org/dc/elements/1.1/relation:"
    xmlns:ldp="http://www.w3.org/ns/ldp#"
    xmlns:ns008="http://purl.org/dc/elements/1.1/identifier:"
    xmlns:xs="http://www.w3.org/2001/XMLSchema"
    xmlns:ns016="http://purl.org/dc/elements/1.1/contributor:"
    xmlns:dcterms="http://purl.org/dc/terms/"
    xmlns:dc="http://purl.org/dc/elements/1.1/"
    xmlns:prov="http://www.w3.org/ns/prov#"
    xmlns:test="info:fedora/test/"
    xmlns:ns015="http://purl.org/dc/elements/1.1/title:"
    xmlns:skos="http://www.w3.org/2004/02/skos/core#"
    xmlns:ns003="http://www.openarchives.org/ore/terms/"
    xmlns:event="http://fedora.info/definitions/v4/event#"
    xmlns:ns001="http://fedora.info/definitions/v4/service#"
    xmlns:rdf="http://www.w3.org/1999/02/22-rdf-syntax-ns#"
    xmlns:ns013="http://purl.org/dc/elements/1.1/type:"
    xmlns:ns006="http://purl.org/dc/elements/1.1/coverage:"
    xmlns:ns014="http://purl.org/dc/elements/1.1/subject:"
    xmlns:iana="http://www.iana.org/assignments/relation/"
    xmlns:ns007="http://purl.org/dc/elements/1.1/date:"
    xmlns:rdfs="http://www.w3.org/2000/01/rdf-schema#"
    xmlns:ns005="http://www.openarchives.org/ore/terms#"
    xmlns:ebucore="http://www.ebu.ch/metadata/ontologies/ebucore/ebucore#"
    xmlns:premis="http://www.loc.gov/premis/rdf/v1#"
    xmlns:owl="http://www.w3.org/2002/07/owl#"
    xmlns:fedora="http://fedora.info/definitions/v4/repository#"
    xmlns:ns002="http://fedora.info/definitions/v4/api-extension#"
    xmlns:ns009="http://purl.org/dc/elements/1.1/description:"
    xmlns:ns017="http://purl.org/dc/elements/1.1/rights:"
    xmlns:xsi="http://www.w3.org/2001/XMLSchema-instance"
    xmlns:foaf="http://xmlns.com/foaf/0.1/"
    xmlns:ns011="http://purl.org/dc/elements/1.1/language:"
    xmlns:ns004="http://pcdm.org/models#" > 
  <rdf:Description rdf:about="http://localhost:9100/mock/fcrepo/rest/path/to/container/fcr:versions/TestVersion1">
    <fedora:created rdf:datatype="http://www.w3.org/2001/XMLSchema#dateTime">2018-03-21T19:43:34.573Z</fedora:created>
    <fedora:hasVersionLabel rdf:datatype="http://www.w3.org/2001/XMLSchema#string">TestVersion1</fedora:hasVersionLabel>
  </rdf:Description>
  <rdf:Description rdf:about="http://localhost:9100/mock/fcrepo/rest/path/to/container/fcr:versions/TestVersion2">
    <fedora:created rdf:datatype="http://www.w3.org/2001/XMLSchema#dateTime">2018-03-21T19:44:48.852Z</fedora:created>
    <fedora:hasVersionLabel rdf:datatype="http://www.w3.org/2001/XMLSchema#string">TestVersion2</fedora:hasVersionLabel>
  </rdf:Description>
  <rdf:Description rdf:about="http://localhost:9100/mock/fcrepo/rest/path/to/container">
    <fedora:hasVersion rdf:resource="http://localhost:9100/mock/fcrepo/rest/path/to/container/fcr:versions/TestVersion2"/>
    <fedora:hasVersion rdf:resource="http://localhost:9100/mock/fcrepo/rest/path/to/container/fcr:versions/TestVersion1"/>
  </rdf:Description>
</rdf:RDF>
